{
  "type" : "DIP",
  "vendor" : "Citrix",
  "id" : "com.microapp.demo.jira.DemoJiraService",
  "version" : "0.1.0",
  "title" : "MICROAPP-9459 Jira integration",
  "description" : "",
  "iconUrl" : "https://ctx-ws-cdn.cloud.com/assets/microapps/exported/JIRA.35cdd2008e8e83479745e5635da3d7f1.svg",
  "masVersion" : "1.0.0-SNAPSHOT.",
  "categories" : [ "DEMO" ],
  "created" : "2020-07-16T12:02:54",
  "supportsOAuthForActions" : false,
  "i18nLanguages" : [ "de", "en", "es", "fr", "ja", "nl", "pt-BR", "zh-CN" ],
  "apps" : [ {
    "uuid" : "3f9016fb-e361-4525-8486-0e1d90df48ce",
    "title" : "My Tickets (Demo)",
    "numberOfEvents" : 2,
    "action" : false
  }, {
    "uuid" : "b0cc7605-ee78-4239-a001-d6101346a6d7",
    "title" : "Create Ticket (Demo)",
    "numberOfEvents" : 0,
    "action" : true
  } ],
  "vaResolvers" : [ ],
  "tags" : [ {
    "tag" : "helpUrl",
    "value" : "https://docs.citrix.com/en-us/citrix-microapps.html"
  } ]
}